bigdl/__init__.py
bigdl/orca/__init__.py
bigdl/orca/common.py
bigdl/orca/cpu_info.py
bigdl/orca/test_zoo_utils.py
bigdl/orca/automl/__init__.py
bigdl/orca/automl/auto_estimator.py
bigdl/orca/automl/hp.py
bigdl/orca/automl/metrics.py
bigdl/orca/automl/pytorch_utils.py
bigdl/orca/automl/model/__init__.py
bigdl/orca/automl/model/abstract.py
bigdl/orca/automl/model/base_keras_model.py
bigdl/orca/automl/model/base_pytorch_model.py
bigdl/orca/automl/search/__init__.py
bigdl/orca/automl/search/base.py
bigdl/orca/automl/search/parameters.py
bigdl/orca/automl/search/tensorboardlogger.py
bigdl/orca/automl/search/utils.py
bigdl/orca/automl/search/ray_tune/__init__.py
bigdl/orca/automl/search/ray_tune/ray_tune_search_engine.py
bigdl/orca/automl/search/ray_tune/utils.py
bigdl/orca/automl/xgboost/XGBoost.py
bigdl/orca/automl/xgboost/__init__.py
bigdl/orca/automl/xgboost/auto_xgb.py
bigdl/orca/data/__init__.py
bigdl/orca/data/elastic_search.py
bigdl/orca/data/file.py
bigdl/orca/data/file_hdfs_cli.py
bigdl/orca/data/ray_xshards.py
bigdl/orca/data/shard.py
bigdl/orca/data/transformer.py
bigdl/orca/data/utils.py
bigdl/orca/data/image/__init__.py
bigdl/orca/data/image/imagenet_dataset.py
bigdl/orca/data/image/parquet_dataset.py
bigdl/orca/data/image/preprocessing.py
bigdl/orca/data/image/tfrecord_dataset.py
bigdl/orca/data/image/utils.py
bigdl/orca/data/image/voc_dataset.py
bigdl/orca/data/pandas/__init__.py
bigdl/orca/data/pandas/preprocessing.py
bigdl/orca/data/tf/__init__.py
bigdl/orca/data/tf/data.py
bigdl/orca/data/tf/tf1_data.py
bigdl/orca/data/tf/tf2_data.py
bigdl/orca/inference/__init__.py
bigdl/orca/inference/inference_model.py
bigdl/orca/learn/__init__.py
bigdl/orca/learn/base_estimator.py
bigdl/orca/learn/dl_cluster.py
bigdl/orca/learn/log_monitor.py
bigdl/orca/learn/metrics.py
bigdl/orca/learn/ray_estimator.py
bigdl/orca/learn/spark_estimator.py
bigdl/orca/learn/trigger.py
bigdl/orca/learn/utils.py
bigdl/orca/learn/bigdl/__init__.py
bigdl/orca/learn/bigdl/estimator.py
bigdl_orca-2.4.0.dist-info/METADATA
bigdl_orca-2.4.0.dist-info/WHEEL
bigdl_orca-2.4.0.dist-info/dependency_links.txt
bigdl_orca-2.4.0.dist-info/top_level.txt
bigdl_orca-2.4.0.dist-info/RECORD
